MANIFEST.in
setup.py
kea2/__init__.py
kea2/cli.py
kea2/log.py
kea2/render.py
kea2/util.py
kea2.egg-info/PKG-INFO
kea2.egg-info/SOURCES.txt
kea2.egg-info/dependency_links.txt
kea2.egg-info/entry_points.txt
kea2.egg-info/requires.txt
kea2.egg-info/top_level.txt
kea2/etc/config/k2rc
kea2/etc/executor/gnu_parallel/command.template
kea2/etc/executor/gnu_parallel/run.template
kea2/etc/executor/simple/command.template
kea2/etc/executor/simple/command.template~
kea2/etc/executor/simple/command_runner.template
kea2/etc/executor/simple/command_runner.template~
kea2/etc/executor/simple/run.template
kea2/etc/template/kea2check.k2
kea2/manage_plugin/__init__.py
kea2/manage_plugin/snippet.py
kea2/plugin/__init__.py
kea2/plugin/executor_gnu_parallel.py
kea2/plugin/executor_parallel.py
kea2/plugin/executor_print.py
kea2/plugin/executor_simple.py
kea2/plugin/inout.py
kea2/plugin/mad.py
kea2/plugin/skip_newer.py
kea2/plugin/twitter.py